cdpchaostoolkit/__init__.py
cdpchaostoolkit/__main__.py
cdpchaostoolkit/check.py
cdpchaostoolkit/cli.py
cdpchaostoolkit/logging.py
cdpchaostoolkit/util.py
cdpchaostoolkit-1.4.2.dist-info/LICENSE
cdpchaostoolkit-1.4.2.dist-info/METADATA
cdpchaostoolkit-1.4.2.dist-info/WHEEL
cdpchaostoolkit-1.4.2.dist-info/entry_points.txt
cdpchaostoolkit-1.4.2.dist-info/top_level.txt
cdpchaostoolkit-1.4.2.dist-info/RECORD
